docs/source/conf.py
tests/__init__.py
tests/conftest.py
tests/test_models.py
tests/test_transforms.py
wetsuit/__init__.py
wetsuit/models.py
wetsuit/transforms.py
wetsuit-0.1.0.dist-info/LICENSE.txt
wetsuit-0.1.0.dist-info/METADATA
wetsuit-0.1.0.dist-info/WHEEL
wetsuit-0.1.0.dist-info/top_level.txt
wetsuit-0.1.0.dist-info/RECORD
