Metadata-Version: 2.1
Name: wetsuit
Version: 0.1.0
Summary: A Scikit-learn style wrapper for H2O estimators.
Author-email: Chris Santiago <cjsantiago@gatech.edu>
License: MIT License
Project-URL: Sourcecode, https://github.com/chris-santiago/wetsuit
Project-URL: Documentation, https://chris-santiago.github.io/wetsuit/
Requires-Python: >=3.7
License-File: LICENSE.txt
Requires-Dist: scikit-learn
Requires-Dist: h2o
Requires-Dist: pandas
Requires-Dist: numpy
Requires-Dist: importlib-metadata
Provides-Extra: build
Requires-Dist: twine ; extra == 'build'
Requires-Dist: wheel ; extra == 'build'
Provides-Extra: dev
Requires-Dist: wetsuit[docs] ; extra == 'dev'
Requires-Dist: wetsuit[tests] ; extra == 'dev'
Requires-Dist: wetsuit[qa] ; extra == 'dev'
Requires-Dist: wetsuit[build] ; extra == 'dev'
Provides-Extra: docs
Requires-Dist: sphinx ; extra == 'docs'
Requires-Dist: sphinx-rtd-theme ; extra == 'docs'
Requires-Dist: myst-parser ; extra == 'docs'
Requires-Dist: tomli ; extra == 'docs'
Provides-Extra: qa
Requires-Dist: pre-commit ; extra == 'qa'
Requires-Dist: black ; extra == 'qa'
Requires-Dist: flake8 ; extra == 'qa'
Requires-Dist: flake8-docstrings ; extra == 'qa'
Requires-Dist: mypy ; extra == 'qa'
Requires-Dist: nox ; extra == 'qa'
Requires-Dist: check-manifest ; extra == 'qa'
Requires-Dist: isort ; extra == 'qa'
Requires-Dist: pylint ; extra == 'qa'
Provides-Extra: tests
Requires-Dist: coverage ; extra == 'tests'
Requires-Dist: pytest ; extra == 'tests'
Requires-Dist: pytest-cov ; extra == 'tests'
Requires-Dist: toml ; extra == 'tests'
Requires-Dist: pre-commit-hooks ; extra == 'tests'
